[
  {
    "type": "answerChangedEvent",
    "runtimeFieldId": "0,0,1",
    "timestamp": 0,
    "answer":
    {
      "type": "simple",
      "value": "true",
      "timestamp": 0
    }
  },

  {
    "type": "answerChangedEvent",
    "runtimeFieldId": "0,0,1",
    "timestamp": 0,
    "answer":
    {
      "type": "simple",
      "value": "Jon",
      "timestamp": 0
    }
  },
  {
    "type": "answerChangedEvent",
    "runtimeFieldId": "0,0,2",
    "timestamp": 0,
    "answer":
    {
      "type": "simple",
      "value": "Snow",
      "timestamp": 0
    }
  },
  {
    "type": "answerChangedEvent",
    "runtimeFieldId": "0,0,3",
    "timestamp": 0,
    "answer":
    {
      "type": "simple",
      "value": "Smith",
      "timestamp": 0
    }
  },
  {
    "type": "answerChangedEvent",
    "runtimeFieldId": "0,0,4",
    "timestamp": 0,
    "answer":
    {
      "type": "simple",
      "value": "1234567890",
      "timestamp": 0
    }
  },
  {
    "type": "answerChangedEvent",
    "runtimeFieldId": "0,0,5",
    "timestamp": 0,
    "answer":
    {
      "type": "simple",
      "value": "${bussinessname}",
      "timestamp": 0
    }
  },
  {
    "type": "answerChangedEvent",
    "runtimeFieldId": "0,0,6",
    "timestamp": 0,
    "answer":
    {
      "type": "simple",
      "value": "12345",
      "timestamp": 0
    }
  },
  {
    "type": "answerChangedEvent",
    "runtimeFieldId": "0,0,7",
    "timestamp": 0,
    "answer":
    {
      "type": "simple",
      "value": "Hospital",
      "timestamp": 0
    }
  },

  {
    "type": "answerChangedEvent",
    "runtimeFieldId": "3,0",
    "timestamp": 0,
    "answer": {
      "type": "simple",
      "value": "Clearing house",
      "timestamp": 0
    }
  },
  {
    "type": "answerChangedEvent",
    "runtimeFieldId": "3,3",
    "timestamp": 0,
    "answer": {
      "type": "simple",
      "value": "wy.providers+${provider}@gmail.com",
      "timestamp": 0
    }
  },
  {
    "type": "answerChangedEvent",
    "runtimeFieldId": "4,0",
    "timestamp": 0,
    "answer": {
      "type": "simple",
      "value": "HHS-Technology",
      "timestamp": 0
    }
  },
  {
    "type": "answerChangedEvent",
    "runtimeFieldId": "4,1",
    "timestamp": 0,
    "answer": {
      "type": "simple",
      "value": "HHS",
      "timestamp": 0
    }
  },
  {
    "type": "answerChangedEvent",
    "runtimeFieldId": "4,2",
    "timestamp": 0,
    "answer": {
      "type": "simple",
      "value": "3.5.13",
      "timestamp": 0
    }
  },
  {
    "type": "answerChangedEvent",
    "runtimeFieldId": "4,3",
    "timestamp": 0,
    "answer": {
      "type": "simple",
      "value": "TCP/IP",
      "timestamp": 0
    }
  }

]