{"name":"Group Provider Status Changing from New to Approved with 2 reviewers and 1 Approver","id":"00-FL-PROJECT/00-FL-REGRESSION/IUFlowStories/RateSetting/Rate_Setting_Automatic/02-Rate_Setting_Automatic_StatusVerification.story;Group Provider Status Changing from New to Approved with 2 reviewers and 1 Approver","testSteps":[{"number":1,"description":"Given user navigated to landing page","duration":5375,"startTime":"2025-08-14T17:21:13.639434+05:30[Asia/Kolkata]","result":"SUCCESS","precondition":false,"children":[{"number":2,"description":"Open landing page","duration":5166,"startTime":"2025-08-14T17:21:13.840165+05:30[Asia/Kolkata]","result":"SUCCESS","precondition":false}]},{"number":3,"description":"And save current {date} to variable \u0027date\u0027","duration":26,"startTime":"2025-08-14T17:21:19.016205+05:30[Asia/Kolkata]","result":"SUCCESS","precondition":false},{"number":4,"description":"And save value \u0027Mediplus Community Service\u0027 to variable \u0027providerLegalBusinessName\u0027","duration":1,"startTime":"2025-08-14T17:21:19.043111+05:30[Asia/Kolkata]","result":"SUCCESS","precondition":false},{"number":5,"description":"When new user logs to Internal User portal with username - {internal.user.dyp+cd@gmail.com} and password - {Internaluser1!}","duration":7958,"startTime":"2025-08-14T17:21:19.044819+05:30[Asia/Kolkata]","result":"SUCCESS","precondition":false,"children":[{"number":6,"description":"Fill username: internal.user.dyp+cd@gmail.com","duration":817,"startTime":"2025-08-14T17:21:19.058852+05:30[Asia/Kolkata]","result":"SUCCESS","precondition":false},{"number":7,"description":"Fill password: Internaluser1!","duration":93,"startTime":"2025-08-14T17:21:19.876600+05:30[Asia/Kolkata]","result":"SUCCESS","precondition":false},{"number":8,"description":"Click new login and wait for loading","duration":7030,"startTime":"2025-08-14T17:21:19.970472+05:30[Asia/Kolkata]","result":"SUCCESS","precondition":false}]},{"number":9,"description":"And implicit wait \u002710\u0027 seconds","duration":10049,"startTime":"2025-08-14T17:21:27.005988+05:30[Asia/Kolkata]","result":"SUCCESS","precondition":false},{"number":10,"description":"When click on new \u0027Agree\u0027 button in the Portal page","duration":6431,"startTime":"2025-08-14T17:21:37.058385+05:30[Asia/Kolkata]","result":"SUCCESS","precondition":false,"children":[{"number":11,"description":"Click new agree button: Agree","duration":6406,"startTime":"2025-08-14T17:21:37.081974+05:30[Asia/Kolkata]","result":"SUCCESS","precondition":false}]},{"number":12,"description":"And implicit wait \u002720\u0027 seconds","duration":20015,"startTime":"2025-08-14T17:21:43.490171+05:30[Asia/Kolkata]","result":"SUCCESS","precondition":false},{"number":13,"description":"!-- When click on Enrollment tab on header","duration":7,"startTime":"2025-08-14T17:22:03.518166+05:30[Asia/Kolkata]","result":"IGNORED","precondition":false},{"number":14,"description":"!-- When implicit wait \u00275\u0027 seconds","duration":0,"startTime":"2025-08-14T17:22:03.527345+05:30[Asia/Kolkata]","result":"IGNORED","precondition":false},{"number":15,"description":"!-- Then search with RequestID \u0027446\u0027","duration":0,"startTime":"2025-08-14T17:22:03.528396+05:30[Asia/Kolkata]","result":"IGNORED","precondition":false},{"number":16,"description":"!-- When implicit wait \u002710\u0027 seconds","duration":0,"startTime":"2025-08-14T17:22:03.529491+05:30[Asia/Kolkata]","result":"IGNORED","precondition":false},{"number":17,"description":"!-- Then check results after search","duration":0,"startTime":"2025-08-14T17:22:03.530427+05:30[Asia/Kolkata]","result":"IGNORED","precondition":false},{"number":18,"description":"!-- When implicit wait \u00275\u0027 seconds","duration":0,"startTime":"2025-08-14T17:22:03.531306+05:30[Asia/Kolkata]","result":"IGNORED","precondition":false},{"number":19,"description":"!-- Then click on the \u0027Entity\u0027 provider","duration":0,"startTime":"2025-08-14T17:22:03.532215+05:30[Asia/Kolkata]","result":"IGNORED","precondition":false},{"number":20,"description":"!-- When implicit wait \u002740\u0027 seconds","duration":0,"startTime":"2025-08-14T17:22:03.533172+05:30[Asia/Kolkata]","result":"IGNORED","precondition":false},{"number":21,"description":"!-- Then verify provider status should be \u0027NEW\u0027 on the Enrollment tab in IU portal","duration":0,"startTime":"2025-08-14T17:22:03.534076+05:30[Asia/Kolkata]","result":"IGNORED","precondition":false},{"number":22,"description":"!-- When click on \u0027Change status\u0027 button from the enrollment details page","duration":0,"startTime":"2025-08-14T17:22:03.534979+05:30[Asia/Kolkata]","result":"IGNORED","precondition":false},{"number":23,"description":"!-- When implicit wait \u00275\u0027 seconds","duration":0,"startTime":"2025-08-14T17:22:03.535866+05:30[Asia/Kolkata]","result":"IGNORED","precondition":false},{"number":24,"description":"!-- When set enrollment request New status to - \u0027Document Review\u0027","duration":0,"startTime":"2025-08-14T17:22:03.537483+05:30[Asia/Kolkata]","result":"IGNORED","precondition":false},{"number":25,"description":"!-- When implicit wait \u00275\u0027 seconds","duration":0,"startTime":"2025-08-14T17:22:03.538327+05:30[Asia/Kolkata]","result":"IGNORED","precondition":false},{"number":26,"description":"!-- And refresh page","duration":0,"startTime":"2025-08-14T17:22:03.539076+05:30[Asia/Kolkata]","result":"IGNORED","precondition":false},{"number":27,"description":"!-- And implicit wait \u002740\u0027 seconds","duration":0,"startTime":"2025-08-14T17:22:03.539856+05:30[Asia/Kolkata]","result":"IGNORED","precondition":false},{"number":28,"description":"!-- When click on \u0027Change status\u0027 button from the enrollment details page","duration":0,"startTime":"2025-08-14T17:22:03.540656+05:30[Asia/Kolkata]","result":"IGNORED","precondition":false},{"number":29,"description":"!-- When implicit wait \u00275\u0027 seconds","duration":1,"startTime":"2025-08-14T17:22:03.541505+05:30[Asia/Kolkata]","result":"IGNORED","precondition":false},{"number":30,"description":"!-- When set enrollment request document status to - \u0027Document Review Approved\u0027","duration":0,"startTime":"2025-08-14T17:22:03.542933+05:30[Asia/Kolkata]","result":"IGNORED","precondition":false},{"number":31,"description":"!-- When implicit wait \u00275\u0027 seconds","duration":0,"startTime":"2025-08-14T17:22:03.543695+05:30[Asia/Kolkata]","result":"IGNORED","precondition":false},{"number":32,"description":"!-- And refresh page","duration":0,"startTime":"2025-08-14T17:22:03.544423+05:30[Asia/Kolkata]","result":"IGNORED","precondition":false},{"number":33,"description":"!-- And implicit wait \u002740\u0027 seconds","duration":1,"startTime":"2025-08-14T17:22:03.545098+05:30[Asia/Kolkata]","result":"IGNORED","precondition":false},{"number":34,"description":"!-- When click on \u0027Change status\u0027 button from the enrollment details page","duration":0,"startTime":"2025-08-14T17:22:03.546879+05:30[Asia/Kolkata]","result":"IGNORED","precondition":false},{"number":35,"description":"!-- When implicit wait \u00275\u0027 seconds","duration":0,"startTime":"2025-08-14T17:22:03.547608+05:30[Asia/Kolkata]","result":"IGNORED","precondition":false},{"number":36,"description":"!-- When set enrollment request ready for screening status to - \u0027Under Screening\u0027","duration":0,"startTime":"2025-08-14T17:22:03.548250+05:30[Asia/Kolkata]","result":"IGNORED","precondition":false},{"number":37,"description":"!-- When implicit wait \u00275\u0027 seconds","duration":0,"startTime":"2025-08-14T17:22:03.548896+05:30[Asia/Kolkata]","result":"IGNORED","precondition":false},{"number":38,"description":"!-- And select provider reason \u0027Moving to Under screening\u0027 and \u0027screening note\u0027 Provider under screening","duration":0,"startTime":"2025-08-14T17:22:03.549536+05:30[Asia/Kolkata]","result":"IGNORED","precondition":false},{"number":39,"description":"!-- When implicit wait \u00275\u0027 seconds","duration":0,"startTime":"2025-08-14T17:22:03.550284+05:30[Asia/Kolkata]","result":"IGNORED","precondition":false},{"number":40,"description":"!-- When click on apply button in under screening page","duration":0,"startTime":"2025-08-14T17:22:03.550987+05:30[Asia/Kolkata]","result":"IGNORED","precondition":false},{"number":41,"description":"!-- When implicit wait \u00275\u0027 seconds","duration":0,"startTime":"2025-08-14T17:22:03.551652+05:30[Asia/Kolkata]","result":"IGNORED","precondition":false},{"number":42,"description":"!-- And refresh page","duration":0,"startTime":"2025-08-14T17:22:03.552379+05:30[Asia/Kolkata]","result":"IGNORED","precondition":false},{"number":43,"description":"!-- When implicit wait \u002710\u0027 seconds","duration":0,"startTime":"2025-08-14T17:22:03.552968+05:30[Asia/Kolkata]","result":"IGNORED","precondition":false},{"number":44,"description":"!-- When submits screening with status \u0027UNDER SCREENING\u0027 and get specific request id and save it to \u0027requestId\u0027 with delay \u002710\u0027","duration":0,"startTime":"2025-08-14T17:22:03.553651+05:30[Asia/Kolkata]","result":"IGNORED","precondition":false},{"number":45,"description":"When implicit wait \u002710\u0027 seconds","duration":10021,"startTime":"2025-08-14T17:22:03.554400+05:30[Asia/Kolkata]","result":"SUCCESS","precondition":false},{"number":46,"description":"When get authorization user \u0027cookies\u0027","duration":284,"startTime":"2025-08-14T17:22:13.576899+05:30[Asia/Kolkata]","result":"SUCCESS","precondition":false,"children":[{"number":47,"description":"Get cookies","duration":225,"startTime":"2025-08-14T17:22:13.635137+05:30[Asia/Kolkata]","result":"SUCCESS","precondition":false}]},{"number":48,"description":"When implicit wait \u002710\u0027 seconds","duration":10019,"startTime":"2025-08-14T17:22:13.862363+05:30[Asia/Kolkata]","result":"SUCCESS","precondition":false},{"number":49,"description":"When replace request id \u0027446\u0027 screening file \u0027100screening.xml\u0027","duration":335,"startTime":"2025-08-14T17:22:23.884478+05:30[Asia/Kolkata]","result":"SUCCESS","precondition":false,"children":[{"number":50,"description":"Replace request id screening file: 446, 100screening.xml","duration":315,"startTime":"2025-08-14T17:22:23.903392+05:30[Asia/Kolkata]","result":"SUCCESS","precondition":false}]},{"number":51,"description":"When implicit wait \u002710\u0027 seconds","duration":10016,"startTime":"2025-08-14T17:22:24.220094+05:30[Asia/Kolkata]","result":"SUCCESS","precondition":false},{"number":52,"description":"When send screening request 1 with file \u0027100screening.xml\u0027 with \u0027${cookies}\u0027","duration":3328,"startTime":"2025-08-14T17:22:34.244294+05:30[Asia/Kolkata]","result":"SUCCESS","precondition":false,"children":[{"number":53,"description":"Send screening api requests: 100screening.xml, /api/screening/import/medversant/, auth_token\u003deyJhbGciOiJIUzUxMiJ9.eyJzdWIiOiJpbnRlcm5hbC51c2VyLmR5cCtjZEBnbWFpbC5jb20iLCJhdXRoIjoiSVUiLCJwYXllcnMiOiJtZWRpY2FpZCIsImp0aSI6IjkxMzgxOWM1LTUwZjktNDFmMS04OTgwLTAxOWI0ZmEzOTY0NyIsImV4cCI6MTc1NTI1ODY4NX0.2ZYWCS6vOe66vw6fXmhgHPokahdgPdj9_M-lfhPyhxi1-KXTKaW9dEcHWQvzhjmvNuh1xUHK5Vb6_C2E3DrVRQ","duration":3313,"startTime":"2025-08-14T17:22:34.258926+05:30[Asia/Kolkata]","result":"SUCCESS","precondition":false}]},{"number":54,"description":"When implicit wait \u002710\u0027 seconds","duration":10009,"startTime":"2025-08-14T17:22:37.573025+05:30[Asia/Kolkata]","result":"SUCCESS","precondition":false},{"number":55,"description":"And refresh page","duration":1346,"startTime":"2025-08-14T17:22:47.584246+05:30[Asia/Kolkata]","result":"SUCCESS","precondition":false},{"number":56,"description":"And implicit wait \u002715\u0027 seconds","duration":15023,"startTime":"2025-08-14T17:22:48.931096+05:30[Asia/Kolkata]","result":"SUCCESS","precondition":false},{"number":57,"description":"When click on {Enrollment} tab on header","duration":216,"startTime":"2025-08-14T17:23:03.957465+05:30[Asia/Kolkata]","result":"SUCCESS","precondition":false,"children":[{"number":58,"description":"Click on header tab: Enrollment","duration":173,"startTime":"2025-08-14T17:23:03.999099+05:30[Asia/Kolkata]","result":"SUCCESS","precondition":false}]},{"number":59,"description":"And implicit wait \u002740\u0027 seconds","duration":40013,"startTime":"2025-08-14T17:23:04.178953+05:30[Asia/Kolkata]","result":"SUCCESS","precondition":false},{"number":60,"description":"Then search with RequestID \u0027446\u0027","duration":3323,"startTime":"2025-08-14T17:23:44.199353+05:30[Asia/Kolkata]","result":"SUCCESS","precondition":false},{"number":61,"description":"Then check results after search","duration":1023,"startTime":"2025-08-14T17:23:47.527+05:30[Asia/Kolkata]","result":"SUCCESS","precondition":false,"children":[{"number":62,"description":"Check search result","duration":1003,"startTime":"2025-08-14T17:23:47.547349+05:30[Asia/Kolkata]","result":"SUCCESS","precondition":false}]},{"number":63,"description":"When implicit wait \u00275\u0027 seconds","duration":5007,"startTime":"2025-08-14T17:23:48.551107+05:30[Asia/Kolkata]","result":"SUCCESS","precondition":false},{"number":64,"description":"Then click on the \u0027Entity\u0027 provider","duration":4732,"startTime":"2025-08-14T17:23:53.559648+05:30[Asia/Kolkata]","result":"SUCCESS","precondition":false,"children":[{"number":65,"description":"Click on enrollment type: Entity","duration":4724,"startTime":"2025-08-14T17:23:53.566776+05:30[Asia/Kolkata]","result":"SUCCESS","precondition":false}]},{"number":66,"description":"When implicit wait \u002710\u0027 seconds","duration":10013,"startTime":"2025-08-14T17:23:58.292857+05:30[Asia/Kolkata]","result":"SUCCESS","precondition":false},{"number":67,"description":"Then verify provider status should be \u0027UNDER CLEARING HOUSE CHECK\u0027 on the Enrollment tab in IU portal","duration":46,"startTime":"2025-08-14T17:24:08.308729+05:30[Asia/Kolkata]","result":"SUCCESS","precondition":false,"children":[{"number":68,"description":"Check provider status: UNDER CLEARING HOUSE CHECK","duration":26,"startTime":"2025-08-14T17:24:08.326568+05:30[Asia/Kolkata]","result":"SUCCESS","precondition":false}]},{"number":69,"description":"When implicit wait \u00272\u0027 seconds","duration":2007,"startTime":"2025-08-14T17:24:08.355387+05:30[Asia/Kolkata]","result":"SUCCESS","precondition":false},{"number":70,"description":"When click on \u0027Change status\u0027 button from the enrollment details page","duration":671,"startTime":"2025-08-14T17:24:10.363836+05:30[Asia/Kolkata]","result":"SUCCESS","precondition":false,"children":[{"number":71,"description":"Click on change status button: Change status","duration":632,"startTime":"2025-08-14T17:24:10.402499+05:30[Asia/Kolkata]","result":"SUCCESS","precondition":false}]},{"number":72,"description":"When implicit wait \u00275\u0027 seconds","duration":5007,"startTime":"2025-08-14T17:24:11.036684+05:30[Asia/Kolkata]","result":"SUCCESS","precondition":false},{"number":73,"description":"When set enrollment request Under Clearing House Check status to - {\u0027Clearing House Check Completed\u0027}","duration":3534,"startTime":"2025-08-14T17:24:16.044671+05:30[Asia/Kolkata]","result":"SUCCESS","precondition":false,"children":[{"number":74,"description":"Set clearing house check: \u0027Clearing House Check Completed\u0027","duration":3517,"startTime":"2025-08-14T17:24:16.049392+05:30[Asia/Kolkata]","result":"SUCCESS","precondition":false}]},{"number":75,"description":"When implicit wait \u00275\u0027 seconds","duration":5006,"startTime":"2025-08-14T17:24:19.579093+05:30[Asia/Kolkata]","result":"SUCCESS","precondition":false},{"number":76,"description":"And select provider reason \u0027Positive Background Results\u0027 and \u0027Clearing House Check Completed note\u0027 Provider under screening","duration":5576,"startTime":"2025-08-14T17:24:24.586881+05:30[Asia/Kolkata]","result":"SUCCESS","precondition":false,"children":[{"number":77,"description":"Set reason for provider termination or reactivatation: Positive Background Results, Clearing House Check Completed note","duration":5527,"startTime":"2025-08-14T17:24:24.635231+05:30[Asia/Kolkata]","result":"SUCCESS","precondition":false}]},{"number":78,"description":"When implicit wait \u00275\u0027 seconds","duration":5010,"startTime":"2025-08-14T17:24:30.164740+05:30[Asia/Kolkata]","result":"SUCCESS","precondition":false},{"number":79,"description":"When click on apply button in under screening page","duration":464,"startTime":"2025-08-14T17:24:35.177106+05:30[Asia/Kolkata]","result":"SUCCESS","precondition":false,"children":[{"number":80,"description":"Click on apply button","duration":458,"startTime":"2025-08-14T17:24:35.182724+05:30[Asia/Kolkata]","result":"SUCCESS","precondition":false}]},{"number":81,"description":"And implicit wait \u002740\u0027 seconds","duration":40015,"startTime":"2025-08-14T17:24:35.641967+05:30[Asia/Kolkata]","result":"SUCCESS","precondition":false},{"number":82,"description":"And refresh page","duration":315,"startTime":"2025-08-14T17:25:15.661072+05:30[Asia/Kolkata]","result":"SUCCESS","precondition":false},{"number":83,"description":"And implicit wait \u002740\u0027 seconds","duration":40015,"startTime":"2025-08-14T17:25:15.976998+05:30[Asia/Kolkata]","result":"SUCCESS","precondition":false},{"number":84,"description":"And refresh page","duration":1718,"startTime":"2025-08-14T17:25:55.993851+05:30[Asia/Kolkata]","result":"SUCCESS","precondition":false},{"number":85,"description":"And implicit wait \u002740\u0027 seconds","duration":40012,"startTime":"2025-08-14T17:25:57.712637+05:30[Asia/Kolkata]","result":"SUCCESS","precondition":false},{"number":86,"description":"When click on \u0027Change status\u0027 button from the enrollment details page","duration":646,"startTime":"2025-08-14T17:26:37.727560+05:30[Asia/Kolkata]","result":"SUCCESS","precondition":false,"children":[{"number":87,"description":"Click on change status button: Change status","duration":637,"startTime":"2025-08-14T17:26:37.735995+05:30[Asia/Kolkata]","result":"SUCCESS","precondition":false}]},{"number":88,"description":"When set to the status for enrollment request status - \u0027Approved\u0027 and set the \u0027${date}\u0027 with reason - \u0027Approved Based Documents\u0027","duration":12662,"startTime":"2025-08-14T17:26:38.374389+05:30[Asia/Kolkata]","result":"SUCCESS","precondition":false,"children":[{"number":89,"description":"Set status2: Approved, Approved Based Documents, 08/14/2025","duration":12657,"startTime":"2025-08-14T17:26:38.376577+05:30[Asia/Kolkata]","result":"SUCCESS","precondition":false}]},{"number":90,"description":"And implicit wait \u002730\u0027 seconds","duration":30019,"startTime":"2025-08-14T17:26:51.037765+05:30[Asia/Kolkata]","result":"SUCCESS","precondition":false},{"number":91,"description":"Then verify provider status should be \u0027APPROVED\u0027 on the Enrollment tab in IU portal","duration":35,"startTime":"2025-08-14T17:27:21.064310+05:30[Asia/Kolkata]","result":"SUCCESS","precondition":false,"children":[{"number":92,"description":"Check provider status: APPROVED","duration":22,"startTime":"2025-08-14T17:27:21.076801+05:30[Asia/Kolkata]","result":"SUCCESS","precondition":false}]},{"number":93,"description":"When log out from IU portal","duration":6161,"startTime":"2025-08-14T17:27:21.100019+05:30[Asia/Kolkata]","result":"SUCCESS","precondition":false,"children":[{"number":94,"description":"Click on user email","duration":39,"startTime":"2025-08-14T17:27:21.106133+05:30[Asia/Kolkata]","result":"SUCCESS","precondition":false},{"number":95,"description":"Select option on user pop up: Log out","duration":6090,"startTime":"2025-08-14T17:27:21.146547+05:30[Asia/Kolkata]","result":"SUCCESS","precondition":false},{"number":96,"description":"Wait for redirected from: https://fl-htgqa-dyp-sb-01.hhstechgroup.com/requests/a7362662-32e0-4f0c-94c6-e99dfa03c1e2","duration":22,"startTime":"2025-08-14T17:27:27.238471+05:30[Asia/Kolkata]","result":"SUCCESS","precondition":false}]}],"userStory":{"id":"02-Rate_Setting_Automatic_StatusVerification","storyName":"02- rate  setting  automatic  status verification","path":"00-FL-PROJECT/00-FL-REGRESSION/IUFlowStories/RateSetting/Rate_Setting_Automatic/02-Rate_Setting_Automatic_StatusVerification.story","narrative":"As a user\nI want to perform an action\nSo that I can achieve a business goal","type":"story"},"featureTag":{"name":"Rate  setting  automatic/02- rate  setting  automatic  status verification","type":"story"},"title":"Group Provider Status Changing from New to Approved with 2 reviewers and 1 Approver","startTime":"2025-08-14T17:21:11.885156+05:30[Asia/Kolkata]","duration":375379,"projectKey":"","sessionId":"bee5db5e5a5ed7e6b9b9ff03bbe0e0db","driver":"chrome","manual":false,"testSource":"JBehave","result":"SUCCESS"}